[
null,
{"id":1,"actions":[{"conditionParam1":1,"conditionParam2":1,"conditionType":1,"rating":5,"skillId":1},{"conditionParam1":0,"conditionParam2":0,"conditionType":0,"rating":4,"skillId":3}],"battlerHue":0,"battlerName":"Actor2_1","dropItems":[{"dataId":1,"denominator":1,"kind":0},{"dataId":1,"denominator":1,"kind":0},{"dataId":1,"denominator":1,"kind":0}],"exp":0,"traits":[],"gold":0,"name":"PLACEHOLDER","note":"<UTB Attack 1>\nInitial X: box.left\nInitial Y: box.top + Math.randomInt(box.width)\nX Speed: 1\nY Speed: 0\nX Accel: 0.01\nY Accel: 0\nCollision Type: rect\nWidth: 10\nHeight: 10\nImage: Command 1\nSpawn Rate: 100\nSpawn Delay: 0\n</UTB Attack 1>","params":[50,0,30,30,30,30,30,30]},
{"id":2,"actions":[{"conditionParam1":0,"conditionParam2":0,"conditionType":0,"rating":5,"skillId":1}],"battlerHue":0,"battlerName":"","dropItems":[{"dataId":1,"denominator":1,"kind":0},{"dataId":1,"denominator":1,"kind":0},{"dataId":1,"denominator":1,"kind":0}],"exp":0,"traits":[{"code":22,"dataId":0,"value":0.95},{"code":22,"dataId":1,"value":0.05},{"code":31,"dataId":1,"value":0}],"gold":0,"name":"El R","note":"","params":[100,0,10,10,10,10,10,10]},
{"id":3,"actions":[{"conditionParam1":0,"conditionParam2":0,"conditionType":0,"rating":5,"skillId":1}],"battlerHue":0,"battlerName":"","dropItems":[{"dataId":1,"denominator":1,"kind":0},{"dataId":1,"denominator":1,"kind":0},{"dataId":1,"denominator":1,"kind":0}],"exp":0,"traits":[{"code":22,"dataId":0,"value":0.95},{"code":22,"dataId":1,"value":0.05},{"code":31,"dataId":1,"value":0}],"gold":0,"name":"","note":"","params":[100,0,10,10,10,10,10,10]},
{"id":4,"actions":[{"conditionParam1":0,"conditionParam2":0,"conditionType":0,"rating":5,"skillId":1}],"battlerHue":0,"battlerName":"","dropItems":[{"dataId":1,"denominator":1,"kind":0},{"dataId":1,"denominator":1,"kind":0},{"dataId":1,"denominator":1,"kind":0}],"exp":0,"traits":[{"code":22,"dataId":0,"value":0.95},{"code":22,"dataId":1,"value":0.05},{"code":31,"dataId":1,"value":0}],"gold":0,"name":"","note":"","params":[100,0,10,10,10,10,10,10]},
{"id":5,"actions":[{"conditionParam1":0,"conditionParam2":0,"conditionType":0,"rating":5,"skillId":1}],"battlerHue":0,"battlerName":"","dropItems":[{"dataId":1,"denominator":1,"kind":0},{"dataId":1,"denominator":1,"kind":0},{"dataId":1,"denominator":1,"kind":0}],"exp":0,"traits":[{"code":22,"dataId":0,"value":0.95},{"code":22,"dataId":1,"value":0.05},{"code":31,"dataId":1,"value":0}],"gold":0,"name":"","note":"","params":[100,0,10,10,10,10,10,10]},
{"id":6,"actions":[{"conditionParam1":0,"conditionParam2":0,"conditionType":0,"rating":5,"skillId":1}],"battlerHue":0,"battlerName":"","dropItems":[{"dataId":1,"denominator":1,"kind":0},{"dataId":1,"denominator":1,"kind":0},{"dataId":1,"denominator":1,"kind":0}],"exp":0,"traits":[{"code":22,"dataId":0,"value":0.95},{"code":22,"dataId":1,"value":0.05},{"code":31,"dataId":1,"value":0}],"gold":0,"name":"","note":"","params":[100,0,10,10,10,10,10,10]},
{"id":7,"actions":[{"conditionParam1":0,"conditionParam2":0,"conditionType":0,"rating":5,"skillId":1}],"battlerHue":0,"battlerName":"","dropItems":[{"dataId":1,"denominator":1,"kind":0},{"dataId":1,"denominator":1,"kind":0},{"dataId":1,"denominator":1,"kind":0}],"exp":0,"traits":[{"code":22,"dataId":0,"value":0.95},{"code":22,"dataId":1,"value":0.05},{"code":31,"dataId":1,"value":0}],"gold":0,"name":"","note":"","params":[100,0,10,10,10,10,10,10]},
{"id":8,"actions":[{"conditionParam1":0,"conditionParam2":0,"conditionType":0,"rating":5,"skillId":1}],"battlerHue":0,"battlerName":"","dropItems":[{"dataId":1,"denominator":1,"kind":0},{"dataId":1,"denominator":1,"kind":0},{"dataId":1,"denominator":1,"kind":0}],"exp":0,"traits":[{"code":22,"dataId":0,"value":0.95},{"code":22,"dataId":1,"value":0.05},{"code":31,"dataId":1,"value":0}],"gold":0,"name":"","note":"","params":[100,0,10,10,10,10,10,10]},
{"id":9,"actions":[{"conditionParam1":0,"conditionParam2":0,"conditionType":0,"rating":5,"skillId":1}],"battlerHue":0,"battlerName":"","dropItems":[{"dataId":1,"denominator":1,"kind":0},{"dataId":1,"denominator":1,"kind":0},{"dataId":1,"denominator":1,"kind":0}],"exp":0,"traits":[{"code":22,"dataId":0,"value":0.95},{"code":22,"dataId":1,"value":0.05},{"code":31,"dataId":1,"value":0}],"gold":0,"name":"","note":"","params":[100,0,10,10,10,10,10,10]},
{"id":10,"actions":[{"conditionParam1":0,"conditionParam2":0,"conditionType":0,"rating":5,"skillId":1}],"battlerHue":0,"battlerName":"","dropItems":[{"dataId":1,"denominator":1,"kind":0},{"dataId":1,"denominator":1,"kind":0},{"dataId":1,"denominator":1,"kind":0}],"exp":0,"traits":[{"code":22,"dataId":0,"value":0.95},{"code":22,"dataId":1,"value":0.05},{"code":31,"dataId":1,"value":0}],"gold":0,"name":"","note":"","params":[100,0,10,10,10,10,10,10]},
{"id":11,"actions":[{"conditionParam1":0,"conditionParam2":0,"conditionType":0,"rating":5,"skillId":1}],"battlerHue":0,"battlerName":"","dropItems":[{"dataId":1,"denominator":1,"kind":0},{"dataId":1,"denominator":1,"kind":0},{"dataId":1,"denominator":1,"kind":0}],"exp":0,"traits":[{"code":22,"dataId":0,"value":0.95},{"code":22,"dataId":1,"value":0.05},{"code":31,"dataId":1,"value":0}],"gold":0,"name":"","note":"","params":[100,0,10,10,10,10,10,10]},
{"id":12,"actions":[{"conditionParam1":0,"conditionParam2":0,"conditionType":0,"rating":5,"skillId":1}],"battlerHue":0,"battlerName":"","dropItems":[{"dataId":1,"denominator":1,"kind":0},{"dataId":1,"denominator":1,"kind":0},{"dataId":1,"denominator":1,"kind":0}],"exp":0,"traits":[{"code":22,"dataId":0,"value":0.95},{"code":22,"dataId":1,"value":0.05},{"code":31,"dataId":1,"value":0}],"gold":0,"name":"","note":"","params":[100,0,10,10,10,10,10,10]},
{"id":13,"actions":[{"conditionParam1":0,"conditionParam2":0,"conditionType":0,"rating":5,"skillId":1}],"battlerHue":0,"battlerName":"","dropItems":[{"dataId":1,"denominator":1,"kind":0},{"dataId":1,"denominator":1,"kind":0},{"dataId":1,"denominator":1,"kind":0}],"exp":0,"traits":[{"code":22,"dataId":0,"value":0.95},{"code":22,"dataId":1,"value":0.05},{"code":31,"dataId":1,"value":0}],"gold":0,"name":"","note":"","params":[100,0,10,10,10,10,10,10]},
{"id":14,"actions":[{"conditionParam1":0,"conditionParam2":0,"conditionType":0,"rating":5,"skillId":1}],"battlerHue":0,"battlerName":"","dropItems":[{"dataId":1,"denominator":1,"kind":0},{"dataId":1,"denominator":1,"kind":0},{"dataId":1,"denominator":1,"kind":0}],"exp":0,"traits":[{"code":22,"dataId":0,"value":0.95},{"code":22,"dataId":1,"value":0.05},{"code":31,"dataId":1,"value":0}],"gold":0,"name":"","note":"","params":[100,0,10,10,10,10,10,10]},
{"id":15,"actions":[{"conditionParam1":0,"conditionParam2":0,"conditionType":0,"rating":5,"skillId":1}],"battlerHue":0,"battlerName":"","dropItems":[{"dataId":1,"denominator":1,"kind":0},{"dataId":1,"denominator":1,"kind":0},{"dataId":1,"denominator":1,"kind":0}],"exp":0,"traits":[{"code":22,"dataId":0,"value":0.95},{"code":22,"dataId":1,"value":0.05},{"code":31,"dataId":1,"value":0}],"gold":0,"name":"","note":"","params":[100,0,10,10,10,10,10,10]},
{"id":16,"actions":[{"conditionParam1":0,"conditionParam2":0,"conditionType":0,"rating":5,"skillId":1}],"battlerHue":0,"battlerName":"","dropItems":[{"dataId":1,"denominator":1,"kind":0},{"dataId":1,"denominator":1,"kind":0},{"dataId":1,"denominator":1,"kind":0}],"exp":0,"traits":[{"code":22,"dataId":0,"value":0.95},{"code":22,"dataId":1,"value":0.05},{"code":31,"dataId":1,"value":0}],"gold":0,"name":"","note":"","params":[100,0,10,10,10,10,10,10]},
{"id":17,"actions":[{"conditionParam1":0,"conditionParam2":0,"conditionType":0,"rating":5,"skillId":1}],"battlerHue":0,"battlerName":"","dropItems":[{"dataId":1,"denominator":1,"kind":0},{"dataId":1,"denominator":1,"kind":0},{"dataId":1,"denominator":1,"kind":0}],"exp":0,"traits":[{"code":22,"dataId":0,"value":0.95},{"code":22,"dataId":1,"value":0.05},{"code":31,"dataId":1,"value":0}],"gold":0,"name":"","note":"","params":[100,0,10,10,10,10,10,10]},
{"id":18,"actions":[{"conditionParam1":0,"conditionParam2":0,"conditionType":0,"rating":5,"skillId":1}],"battlerHue":0,"battlerName":"","dropItems":[{"dataId":1,"denominator":1,"kind":0},{"dataId":1,"denominator":1,"kind":0},{"dataId":1,"denominator":1,"kind":0}],"exp":0,"traits":[{"code":22,"dataId":0,"value":0.95},{"code":22,"dataId":1,"value":0.05},{"code":31,"dataId":1,"value":0}],"gold":0,"name":"","note":"","params":[100,0,10,10,10,10,10,10]},
{"id":19,"actions":[{"conditionParam1":0,"conditionParam2":0,"conditionType":0,"rating":5,"skillId":1}],"battlerHue":0,"battlerName":"","dropItems":[{"dataId":1,"denominator":1,"kind":0},{"dataId":1,"denominator":1,"kind":0},{"dataId":1,"denominator":1,"kind":0}],"exp":0,"traits":[{"code":22,"dataId":0,"value":0.95},{"code":22,"dataId":1,"value":0.05},{"code":31,"dataId":1,"value":0}],"gold":0,"name":"","note":"","params":[100,0,10,10,10,10,10,10]},
{"id":20,"actions":[{"conditionParam1":0,"conditionParam2":0,"conditionType":0,"rating":5,"skillId":1}],"battlerHue":0,"battlerName":"","dropItems":[{"dataId":1,"denominator":1,"kind":0},{"dataId":1,"denominator":1,"kind":0},{"dataId":1,"denominator":1,"kind":0}],"exp":0,"traits":[{"code":22,"dataId":0,"value":0.95},{"code":22,"dataId":1,"value":0.05},{"code":31,"dataId":1,"value":0}],"gold":0,"name":"","note":"","params":[100,0,10,10,10,10,10,10]},
{"id":21,"actions":[{"conditionParam1":0,"conditionParam2":0,"conditionType":0,"rating":5,"skillId":1}],"battlerHue":0,"battlerName":"","dropItems":[{"dataId":1,"denominator":1,"kind":0},{"dataId":1,"denominator":1,"kind":0},{"dataId":1,"denominator":1,"kind":0}],"exp":0,"traits":[{"code":22,"dataId":0,"value":0.95},{"code":22,"dataId":1,"value":0.05},{"code":31,"dataId":1,"value":0}],"gold":0,"name":"","note":"","params":[100,0,10,10,10,10,10,10]},
{"id":22,"actions":[{"conditionParam1":0,"conditionParam2":0,"conditionType":0,"rating":5,"skillId":1}],"battlerHue":0,"battlerName":"","dropItems":[{"dataId":1,"denominator":1,"kind":0},{"dataId":1,"denominator":1,"kind":0},{"dataId":1,"denominator":1,"kind":0}],"exp":0,"traits":[{"code":22,"dataId":0,"value":0.95},{"code":22,"dataId":1,"value":0.05},{"code":31,"dataId":1,"value":0}],"gold":0,"name":"","note":"","params":[100,0,10,10,10,10,10,10]},
{"id":23,"actions":[{"conditionParam1":0,"conditionParam2":0,"conditionType":0,"rating":5,"skillId":1}],"battlerHue":0,"battlerName":"","dropItems":[{"dataId":1,"denominator":1,"kind":0},{"dataId":1,"denominator":1,"kind":0},{"dataId":1,"denominator":1,"kind":0}],"exp":0,"traits":[{"code":22,"dataId":0,"value":0.95},{"code":22,"dataId":1,"value":0.05},{"code":31,"dataId":1,"value":0}],"gold":0,"name":"","note":"","params":[100,0,10,10,10,10,10,10]},
{"id":24,"actions":[{"conditionParam1":0,"conditionParam2":0,"conditionType":0,"rating":5,"skillId":1}],"battlerHue":0,"battlerName":"","dropItems":[{"dataId":1,"denominator":1,"kind":0},{"dataId":1,"denominator":1,"kind":0},{"dataId":1,"denominator":1,"kind":0}],"exp":0,"traits":[{"code":22,"dataId":0,"value":0.95},{"code":22,"dataId":1,"value":0.05},{"code":31,"dataId":1,"value":0}],"gold":0,"name":"","note":"","params":[100,0,10,10,10,10,10,10]},
{"id":25,"actions":[{"conditionParam1":0,"conditionParam2":0,"conditionType":0,"rating":5,"skillId":1}],"battlerHue":0,"battlerName":"","dropItems":[{"dataId":1,"denominator":1,"kind":0},{"dataId":1,"denominator":1,"kind":0},{"dataId":1,"denominator":1,"kind":0}],"exp":0,"traits":[{"code":22,"dataId":0,"value":0.95},{"code":22,"dataId":1,"value":0.05},{"code":31,"dataId":1,"value":0}],"gold":0,"name":"","note":"","params":[100,0,10,10,10,10,10,10]},
{"id":26,"actions":[{"conditionParam1":0,"conditionParam2":0,"conditionType":0,"rating":5,"skillId":1}],"battlerHue":0,"battlerName":"","dropItems":[{"dataId":1,"denominator":1,"kind":0},{"dataId":1,"denominator":1,"kind":0},{"dataId":1,"denominator":1,"kind":0}],"exp":0,"traits":[{"code":22,"dataId":0,"value":0.95},{"code":22,"dataId":1,"value":0.05},{"code":31,"dataId":1,"value":0}],"gold":0,"name":"","note":"","params":[100,0,10,10,10,10,10,10]},
{"id":27,"actions":[{"conditionParam1":0,"conditionParam2":0,"conditionType":0,"rating":5,"skillId":1}],"battlerHue":0,"battlerName":"","dropItems":[{"dataId":1,"denominator":1,"kind":0},{"dataId":1,"denominator":1,"kind":0},{"dataId":1,"denominator":1,"kind":0}],"exp":0,"traits":[{"code":22,"dataId":0,"value":0.95},{"code":22,"dataId":1,"value":0.05},{"code":31,"dataId":1,"value":0}],"gold":0,"name":"","note":"","params":[100,0,10,10,10,10,10,10]},
{"id":28,"actions":[{"conditionParam1":0,"conditionParam2":0,"conditionType":0,"rating":5,"skillId":1}],"battlerHue":0,"battlerName":"","dropItems":[{"dataId":1,"denominator":1,"kind":0},{"dataId":1,"denominator":1,"kind":0},{"dataId":1,"denominator":1,"kind":0}],"exp":0,"traits":[{"code":22,"dataId":0,"value":0.95},{"code":22,"dataId":1,"value":0.05},{"code":31,"dataId":1,"value":0}],"gold":0,"name":"","note":"","params":[100,0,10,10,10,10,10,10]},
{"id":29,"actions":[{"conditionParam1":0,"conditionParam2":0,"conditionType":0,"rating":5,"skillId":1}],"battlerHue":0,"battlerName":"","dropItems":[{"dataId":1,"denominator":1,"kind":0},{"dataId":1,"denominator":1,"kind":0},{"dataId":1,"denominator":1,"kind":0}],"exp":0,"traits":[{"code":22,"dataId":0,"value":0.95},{"code":22,"dataId":1,"value":0.05},{"code":31,"dataId":1,"value":0}],"gold":0,"name":"","note":"","params":[100,0,10,10,10,10,10,10]},
{"id":30,"actions":[{"conditionParam1":0,"conditionParam2":0,"conditionType":0,"rating":5,"skillId":1}],"battlerHue":0,"battlerName":"","dropItems":[{"dataId":1,"denominator":1,"kind":0},{"dataId":1,"denominator":1,"kind":0},{"dataId":1,"denominator":1,"kind":0}],"exp":0,"traits":[{"code":22,"dataId":0,"value":0.95},{"code":22,"dataId":1,"value":0.05},{"code":31,"dataId":1,"value":0}],"gold":0,"name":"","note":"","params":[100,0,10,10,10,10,10,10]}
]